checkoutmanager/__init__.py
checkoutmanager/config.py
checkoutmanager/dirinfo.py
checkoutmanager/executors.py
checkoutmanager/runner.py
checkoutmanager/sample.cfg
checkoutmanager/utils.py
checkoutmanager/tests/__init__.py
checkoutmanager/tests/config.txt
checkoutmanager/tests/conftest.py
checkoutmanager/tests/custom_actions.py
checkoutmanager/tests/custom_actions.txt
checkoutmanager/tests/dirinfo.txt
checkoutmanager/tests/sample.txt
checkoutmanager/tests/testconfig.cfg
checkoutmanager/tests/utils.txt
checkoutmanager-3.1.dist-info/LICENSE.GPL
checkoutmanager-3.1.dist-info/METADATA
checkoutmanager-3.1.dist-info/WHEEL
checkoutmanager-3.1.dist-info/entry_points.txt
checkoutmanager-3.1.dist-info/top_level.txt
checkoutmanager-3.1.dist-info/RECORD
