Metadata-Version: 2.2
Name: checkoutmanager
Version: 3.1
Summary: Gives you overview and control over your git/hg/bzr/svn checkouts/clones.
Home-page: http://reinout.vanrees.org
Author: Reinout van Rees
Author-email: reinout@vanrees.org
License: GPL
Classifier: Development Status :: 6 - Mature
Classifier: Environment :: Console
Classifier: License :: OSI Approved :: GNU General Public License (GPL)
Classifier: Operating System :: MacOS :: MacOS X
Classifier: Operating System :: Microsoft :: Windows
Classifier: Operating System :: POSIX
Classifier: Programming Language :: Python :: 3
License-File: LICENSE.GPL
Requires-Dist: setuptools
Provides-Extra: test
Requires-Dist: pytest; extra == "test"
Dynamic: author
Dynamic: author-email
Dynamic: classifier
Dynamic: description
Dynamic: home-page
Dynamic: license
Dynamic: provides-extra
Dynamic: requires-dist
Dynamic: summary
